Workbook

Sheet Index Data
A1: Date | B1: =+'Price & Other Market Data'!B3 -> 46120
A3: Index | B3: Closing | C3: Change | D3: 46081 | E3: Change since takeover
A4: S&P 500 | B4: =_xlfn.XLOOKUP(A4,'Price & Other Market Data'!$A$9:$A$13,'Price & Other Market Data'!$C$9:$C$13) -> 6824.66 | C4: =_xlfn.XLOOKUP(A4,'Price & Other Market Data'!$A$9:$A$13,'Price & Other Market Data'!$D$9:$D$13)/100 -> 0.0062
A5: Dow Jones | B5: =_xlfn.XLOOKUP(A5,'Price & Other Market Data'!$A$9:$A$13,'Price & Other Market Data'!$C$9:$C$13) -> 48185.8 | C5: =_xlfn.XLOOKUP(A5,'Price & Other Market Data'!$A$9:$A$13,'Price & Other Market Data'!$D$9:$D$13)/100 -> 0.0058
A6: NASDAQ | B6: =_xlfn.XLOOKUP(A6,'Price & Other Market Data'!$A$9:$A$13,'Price & Other Market Data'!$C$9:$C$13) -> 22822.42 | C6: =_xlfn.XLOOKUP(A6,'Price & Other Market Data'!$A$9:$A$13,'Price & Other Market Data'!$D$9:$D$13)/100 -> 0.0083
A7: Russell 3000 | B7: =_xlfn.XLOOKUP(A7,'Price & Other Market Data'!$A$9:$A$13,'Price & Other Market Data'!$C$9:$C$13) -> 3883.54 | C7: =_xlfn.XLOOKUP(A7,'Price & Other Market Data'!$A$9:$A$13,'Price & Other Market Data'!$D$9:$D$13)/100 -> 0.0055
A8: S&P Total return | B8: =_xlfn.XLOOKUP(A8,'Price & Other Market Data'!$A$9:$A$13,'Price & Other Market Data'!$C$9:$C$13) -> 15225.18 | C8: =_xlfn.XLOOKUP(A8,'Price & Other Market Data'!$A$9:$A$13,'Price & Other Market Data'!$D$9:$D$13)/100 -> 0.0062 | D8: 15323.8 | E8: =B8/D8-1 -> -0.0064357405

Sheet LH Holding
D1: Total | H1: =SUM(H3:H76) -> 10973622
C3: Cash | D3: UTM MCC POOL ACTIVE RESERVE | H3: =_xlfn.XLOOKUP(D3,'LH_Holding_Custody T'!F:F,'LH_Holding_Custody T'!J:J) -> 127655.16 | I3: =H3/$H$1 -> 0.01163291
A4: Equity | B4: Manual | C4: Enriched | D4: Google | E4: Holdings | F4: Holdings | G4: Google | H4: Enriched | I4: Enriched | J4: Manual | K4: Google | L4: Google | M4: Google
A5: BBG Ticker | B5: Custodian Ticker | C5: Google Ticker | D5: Description | E5: Date | F5: Holdings | G5: Price T | H5: Market Val T | I5: Weight T | J5: Type | K5: Daily Change | L5: 52W High | M5: 52W Low
A6: =B6&$A$4 -> META US Equity | B6: META US | C6: =SUBSTITUTE(REPLACE(B6,LEN(B6)-2,3,""),"/",".") -> META | D6: =_xlfn.XLOOKUP(C6,'Price & Other Market Data'!F:F,'Price & Other Market Data'!I:I) -> Meta Platforms Inc | E6: =+'Price & Other Market Data'!$B$3 -> 46120 | F6: =_xlfn.XLOOKUP(B6,'LH_Holding_Custody T'!G:G,'LH_Holding_Custody T'!J:J) -> 229 | G6: =_xlfn.XLOOKUP(C6,'Price & Other Market Data'!F:F,'Price & Other Market Data'!H:H) -> 612.42 | H6: =F6*G6 -> 140244.18 | I6: =H6/$H$1 -> 0.012780117 | J6: Alpha | K6: =_xlfn.XLOOKUP(C6,'Price & Other Market Data'!$F:$F,'Price & Other Market Data'!J:J) -> 0.0261 | L6: =_xlfn.XLOOKUP(C6,'Price & Other Market Data'!$F:$F,'Price & Other Market Data'!K:K) -> 796.25 | M6: =_xlfn.XLOOKUP(C6,'Price & Other Market Data'!$F:$F,'Price & Other Market Data'!L:L) -> 479.8
A7: =B7&$A$4 -> PEP US Equity | B7: PEP US | C7: =SUBSTITUTE(REPLACE(B7,LEN(B7)-2,3,""),"/",".") -> PEP | D7: =_xlfn.XLOOKUP(C7,'Price & Other Market Data'!F:F,'Price & Other Market Data'!I:I) -> PepsiCo Inc | E7: =+'Price & Other Market Data'!$B$3 -> 46120 | F7: =_xlfn.XLOOKUP(B7,'LH_Holding_Custody T'!G:G,'LH_Holding_Custody T'!J:J) -> 442 | G7: =_xlfn.XLOOKUP(C7,'Price & Other Market Data'!F:F,'Price & Other Market Data'!H:H) -> 154.8 | H7: =F7*G7 -> 68421.6 | I7: =H7/$H$1 -> 0.006235097 | J7: Beta | K7: =_xlfn.XLOOKUP(C7,'Price & Other Market Data'!$F:$F,'Price & Other Market Data'!J:J) -> 0.0174 | L7: =_xlfn.XLOOKUP(C7,'Price & Other Market Data'!$F:$F,'Price & Other Market Data'!K:K) -> 171.48 | M7: =_xlfn.XLOOKUP(C7,'Price & Other Market Data'!$F:$F,'Price & Other Market Data'!L:L) -> 127.6
A8: =B8&$A$4 -> PG US Equity | B8: PG US | C8: =SUBSTITUTE(REPLACE(B8,LEN(B8)-2,3,""),"/",".") -> PG | D8: =_xlfn.XLOOKUP(C8,'Price & Other Market Data'!F:F,'Price & Other Market Data'!I:I) -> Procter & Gamble Co | E8: =+'Price & Other Market Data'!$B$3 -> 46120 | F8: =_xlfn.XLOOKUP(B8,'LH_Holding_Custody T'!G:G,'LH_Holding_Custody T'!J:J) -> 372 | G8: =_xlfn.XLOOKUP(C8,'Price & Other Market Data'!F:F,'Price & Other Market Data'!H:H) -> 144.9 | H8: =F8*G8 -> 53902.8 | I8: =H8/$H$1 -> 0.0049120334 | J8: ETF | K8: =_xlfn.XLOOKUP(C8,'Price & Other Market Data'!$F:$F,'Price & Other Market Data'!J:J) -> 0.0121 | L8: =_xlfn.XLOOKUP(C8,'Price & Other Market Data'!$F:$F,'Price & Other Market Data'!K:K) -> 171.65 | M8: =_xlfn.XLOOKUP(C8,'Price & Other Market Data'!$F:$F,'Price & Other Market Data'!L:L) -> 137.62
A9: =B9&$A$4 -> MRNA US Equity | B9: MRNA US | C9: =SUBSTITUTE(REPLACE(B9,LEN(B9)-2,3,""),"/",".") -> MRNA | D9: =_xlfn.XLOOKUP(C9,'Price & Other Market Data'!F:F,'Price & Other Market Data'!I:I) -> Moderna Inc | E9: =+'Price & Other Market Data'!$B$3 -> 46120 | F9: =_xlfn.XLOOKUP(B9,'LH_Holding_Custody T'!G:G,'LH_Holding_Custody T'!J:J) -> 790 | G9: =_xlfn.XLOOKUP(C9,'Price & Other Market Data'!F:F,'Price & Other Market Data'!H:H) -> 52.1 | H9: =F9*G9 -> 41159 | I9: =H9/$H$1 -> 0.0037507214 | J9: Alpha | K9: =_xlfn.XLOOKUP(C9,'Price & Other Market Data'!$F:$F,'Price & Other Market Data'!J:J) -> -0.0157 | L9: =_xlfn.XLOOKUP(C9,'Price & Other Market Data'!$F:$F,'Price & Other Market Data'!K:K) -> 59.55 | M9: =_xlfn.XLOOKUP(C9,'Price & Other Market Data'!$F:$F,'Price & Other Market Data'!L:L) -> 22.28
A10: =B10&$A$4 -> XLU US Equity | B10: XLU US | C10: =SUBSTITUTE(REPLACE(B10,LEN(B10)-2,3,""),"/",".") -> XLU | D10: =_xlfn.XLOOKUP(C10,'Price & Other Market Data'!F:F,'Price & Other Market Data'!I:I) -> State Street Utilities Select Sector SPDR ETF | E10: =+'Price & Other Market Data'!$B$3 -> 46120 | F10: =_xlfn.XLOOKUP(B10,'LH_Holding_Custody T'!G:G,'LH_Holding_Custody T'!J:J) -> 2394 | G10: =_xlfn.XLOOKUP(C10,'Price & Other Market Data'!F:F,'Price & Other Market Data'!H:H) -> 46.78 | H10: =F10*G10 -> 111991.32 | I10: =H10/$H$1 -> 0.010205501 | J10: Beta | K10: =_xlfn.XLOOKUP(C10,'Price & Other Market Data'!$F:$F,'Price & Other Market Data'!J:J) -> 0.0079 | L10: =_xlfn.XLOOKUP(C10,'Price & Other Market Data'!$F:$F,'Price & Other Market Data'!K:K) -> 47.8 | M10: =_xlfn.XLOOKUP(C10,'Price & Other Market Data'!$F:$F,'Price & Other Market Data'!L:L) -> 35.51
A11: =B11&$A$4 -> XOM US Equity | B11: XOM US | C11: =SUBSTITUTE(REPLACE(B11,LEN(B11)-2,3,""),"/",".") -> XOM | D11: =_xlfn.XLOOKUP(C11,'Price & Other Market Data'!F:F,'Price & Other Market Data'!I:I) -> Exxon Mobil Corp | E11: =+'Price & Other Market Data'!$B$3 -> 46120 | F11: =_xlfn.XLOOKUP(B11,'LH_Holding_Custody T'!G:G,'LH_Holding_Custody T'!J:J) -> 823 | G11: =_xlfn.XLOOKUP(C11,'Price & Other Market Data'!F:F,'Price & Other Market Data'!H:H) -> 156.22 | H11: =F11*G11 -> 128569.06 | I11: =H11/$H$1 -> 0.011716191 | J11: ETF | K11: =_xlfn.XLOOKUP(C11,'Price & Other Market Data'!$F:$F,'Price & Other Market Data'!J:J) -> -0.0076 | L11: =_xlfn.XLOOKUP(C11,'Price & Other Market Data'!$F:$F,'Price & Other Market Data'!K:K) -> 176.41 | M11: =_xlfn.XLOOKUP(C11,'Price & Other Market Data'!$F:$F,'Price & Other Market Data'!L:L) -> 97.8
A12: =B12&$A$4 -> PLTR US Equity | B12: PLTR US | C12: =SUBSTITUTE(REPLACE(B12,LEN(B12)-2,3,""),"/",".") -> PLTR | D12: =_xlfn.XLOOKUP(C12,'Price & Other Market Data'!F:F,'Price & Other Market Data'!I:I) -> Palantir Technologies Inc | E12: =+'Price & Other Market Data'!$B$3 -> 46120 | F12: =_xlfn.XLOOKUP(B12,'LH_Holding_Custody T'!G:G,'LH_Holding_Custody T'!J:J) -> 357 | G12: =_xlfn.XLOOKUP(C12,'Price & Other Market Data'!F:F,'Price & Other Market Data'!H:H) -> 140.76 | H12: =F12*G12 -> 50251.32 | I12: =H12/$H$1 -> 0.0045792828 | J12: Alpha | K12: =_xlfn.XLOOKUP(C12,'Price & Other Market Data'!$F:$F,'Price & Other Market Data'!J:J) -> -0.0726 | L12: =_xlfn.XLOOKUP(C12,'Price & Other Market Data'!$F:$F,'Price & Other Market Data'!K:K) -> 207.52 | M12: =_xlfn.XLOOKUP(C12,'Price & Other Market Data'!$F:$F,'Price & Other Market Data'!L:L) -> 84.14
A13: =B13&$A$4 -> KGS US Equity | B13: KGS US | C13: =SUBSTITUTE(REPLACE(B13,LEN(B13)-2,3,""),"/",".") -> KGS | D13: =_xlfn.XLOOKUP(C13,'Price & Other Market Data'!F:F,'Price & Other Market Data'!I:I) -> Kodiak Gas Services Inc | E13: =+'Price & Other Market Data'!$B$3 -> 46120 | F13: =_xlfn.XLOOKUP(B13,'LH_Holding_Custody T'!G:G,'LH_Holding_Custody T'!J:J) -> 2796 | G13: =_xlfn.XLOOKUP(C13,'Price & Other Market Data'!F:F,'Price & Other Market Data'!H:H) -> 60.23 | H13: =F13*G13 -> 168403.08 | I13: =H13/$H$1 -> 0.01534617 | J13: Beta | K13: =_xlfn.XLOOKUP(C13,'Price & Other Market Data'!$F:$F,'Price & Other Market Data'!J:J) -> 0.0025 | L13: =_xlfn.XLOOKUP(C13,'Price & Other Market Data'!$F:$F,'Price & Other Market Data'!K:K) -> 61.48 | M13: =_xlfn.XLOOKUP(C13,'Price & Other Market Data'!$F:$F,'Price & Other Market Data'!L:L) -> 30.06
A14: =B14&$A$4 -> XLK US Equity | B14: XLK US | C14: =SUBSTITUTE(REPLACE(B14,LEN(B14)-2,3,""),"/",".") -> XLK | D14: =_xlfn.XLOOKUP(C14,'Price & Other Market Data'!F:F,'Price & Other Market Data'!I:I) -> State Street Technology Select Sector SPDR ETF | E14: =+'Price & Other Market Data'!$B$3 -> 46120 | F14: =_xlfn.XLOOKUP(B14,'LH_Holding_Custody T'!G:G,'LH_Holding_Custody T'!J:J) -> 4544 | G14: =_xlfn.XLOOKUP(C14,'Price & Other Market Data'!F:F,'Price & Other Market Data'!H:H) -> 141.69 | H14: =F14*G14 -> 643839.36 | I14: =H14/$H$1 -> 0.058671543 | J14: ETF | K14: =_xlfn.XLOOKUP(C14,'Price & Other Market Data'!$F:$F,'Price & Other Market Data'!J:J) -> 0.0027 | L14: =_xlfn.XLOOKUP(C14,'Price & Other Market Data'!$F:$F,'Price & Other Market Data'!K:K) -> 152.99 | M14: =_xlfn.XLOOKUP(C14,'Price & Other Market Data'!$F:$F,'Price & Other Market Data'!L:L) -> 89.94
A15: =B15&$A$4 -> XLP US Equity | B15: XLP US | C15: =SUBSTITUTE(REPLACE(B15,LEN(B15)-2,3,""),"/",".") -> XLP | D15: =_xlfn.XLOOKUP(C15,'Price & Other Market Data'!F:F,'Price & Other Market Data'!I:I) -> State Street Cons Staples Sel Sec SPDR Inc ETF | E15: =+'Price & Other Market Data'!$B$3 -> 46120 | F15: =_xlfn.XLOOKUP(B15,'LH_Holding_Custody T'!G:G,'LH_Holding_Custody T'!J:J) -> 1106 | G15: =_xlfn.XLOOKUP(C15,'Price & Other Market Data'!F:F,'Price & Other Market Data'!H:H) -> 82.78 | H15: =F15*G15 -> 91554.68 | I15: =H15/$H$1 -> 0.0083431593 | J15: Alpha | K15: =_xlfn.XLOOKUP(C15,'Price & Other Market Data'!$F:$F,'Price & Other Market Data'!J:J) -> 0.0081 | L15: =_xlfn.XLOOKUP(C15,'Price & Other Market Data'!$F:$F,'Price & Other Market Data'!K:K) -> 90.14 | M15: =_xlfn.XLOOKUP(C15,'Price & Other Market Data'!$F:$F,'Price & Other Market Data'!L:L) -> 75.16
A16: =B16&$A$4 -> RSI US Equity | B16: RSI US | C16: =SUBSTITUTE(REPLACE(B16,LEN(B16)-2,3,""),"/",".") -> RSI | D16: =_xlfn.XLOOKUP(C16,'Price & Other Market Data'!F:F,'Price & Other Market Data'!I:I) -> Rush Street Interactive Inc | E16: =+'Price & Other Market Data'!$B$3 -> 46120 | F16: =_xlfn.XLOOKUP(B16,'LH_Holding_Custody T'!G:G,'LH_Holding_Custody T'!J:J) -> 966 | G16: =_xlfn.XLOOKUP(C16,'Price & Other Market Data'!F:F,'Price & Other Market Data'!H:H) -> 22.21 | H16: =F16*G16 -> 21454.86 | I16: =H16/$H$1 -> 0.0019551301 | J16: Beta | K16: =_xlfn.XLOOKUP(C16,'Price & Other Market Data'!$F:$F,'Price & Other Market Data'!J:J) -> -0.036 | L16: =_xlfn.XLOOKUP(C16,'Price & Other Market Data'!$F:$F,'Price & Other Market Data'!K:K) -> 23.15 | M16: =_xlfn.XLOOKUP(C16,'Price & Other Market Data'!$F:$F,'Price & Other Market Data'!L:L) -> 10.88
A17: =B17&$A$4 -> XLB US Equity | B17: XLB US | C17: =SUBSTITUTE(REPLACE(B17,LEN(B17)-2,3,""),"/",".") -> XLB | D17: =_xlfn.XLOOKUP(C17,'Price & Other Market Data'!F:F,'Price & Other Market Data'!I:I) -> State Street Materials Select Sector SPDR ETF | E17: =+'Price & Other Market Data'!$B$3 -> 46120 | F17: =_xlfn.XLOOKUP(B17,'LH_Holding_Custody T'!G:G,'LH_Holding_Custody T'!J:J) -> 755 | G17: =_xlfn.XLOOKUP(C17,'Price & Other Market Data'!F:F,'Price & Other Market Data'!H:H) -> 51.75 | H17: =F17*G17 -> 39071.25 | I17: =H17/$H$1 -> 0.0035604697 | J17: Alpha | K17: =_xlfn.XLOOKUP(C17,'Price & Other Market Data'!$F:$F,'Price & Other Market Data'!J:J) -> -0.0015 | L17: =_xlfn.XLOOKUP(C17,'Price & Other Market Data'!$F:$F,'Price & Other Market Data'!K:K) -> 54.14 | M17: =_xlfn.XLOOKUP(C17,'Price & Other Market Data'!$F:$F,'Price & Other Market Data'!L:L) -> 36.88
... A76: =B76&$A$4 -> NFLX US Equity | B76: NFLX US | C76: =SUBSTITUTE(REPLACE(B76,LEN(B76)-2,3,""),"/",".") -> NFLX | D76: =_xlfn.XLOOKUP(C76,'Price & Other Market Data'!F:F,'Price & Other Market Data'!I:I) -> Netflix Inc | E76: =+'Price & Other Market Data'!$B$3 -> 46120 | F76: =_xlfn.XLOOKUP(B76,'LH_Holding_Custody T'!G:G,'LH_Holding_Custody T'!J:J) -> 450 | G76: =_xlfn.XLOOKUP(C76,'Price & Other Market Data'!F:F,'Price & Other Market Data'!H:H) -> 99.39 | H76: =F76*G76 -> 44725.5 | I76: =H76/$H$1 -> 0.004075728 | J76: ETF | K76: =_xlfn.XLOOKUP(C76,'Price & Other Market Data'!$F:$F,'Price & Other Market Data'!J:J) -> 0.0272 | L76: =_xlfn.XLOOKUP(C76,'Price & Other Market Data'!$F:$F,'Price & Other Market Data'!K:K) -> 134.12 | M76: =_xlfn.XLOOKUP(C76,'Price & Other Market Data'!$F:$F,'Price & Other Market Data'!L:L) -> 75.01

Sheet Price & Other Market Data
A1: symbol | B1: IVV | F1: Ticker | G1: Date | H1: Close | I1: Description | J1: Daily Change | K1: 52W High | L1: 52W Low
A2: attribute | B2: close | F2: AAPL | G2: 46120 | H2: 258.9 | I2: Apple Inc | J2: 0.0061 | K2: 288.61 | L2: 183
A3: start_date | B3: 46120 | G3: Date | H3: Close
A4: num_days or end_date | B4: 30 | F4: ACN | G4: 46120 | H4: 193.84 | I4: Accenture Plc | J4: -0.0322 | K4: 325.71 | L4: 182.38
A5: interval | B5: 7 | G5: Date | H5: Close
A6: start_date less 1 | B6: 46119 | F6: AEM | G6: 46120 | H6: 215.59 | I6: Agnico Eagle Mines Ltd | J6: 0.0038 | K6: 255.24 | L6: 103.38
G7: Date | H7: Close
F8: AMZN | G8: 46120 | H8: 221.25 | I8: Amazon.com Inc | J8: 0.056 | K8: 258.6 | L8: 165.29
A9: S&P 500 | B9: INDEXSP:.INX | C9: 6824.66 | D9: 0.62 | G9: Date | H9: Close
A10: Dow Jones | B10: .DJI | C10: 48185.8 | D10: 0.58 | F10: ANET | G10: 46120 | H10: 145.07 | I10: Arista Networks Inc | J10: 0.0068 | K10: 164.94 | L10: 66.59
A11: NASDAQ | B11: INDEXNASDAQ:.IXIC | C11: 22822.42 | D11: 0.83 | G11: Date | H11: Close
A12: Russell 3000 | B12: RUA | C12: 3883.54 | D12: 0.55 | F12: ASML | G12: 46120 | H12: 1421.05 | I12: ASML Holding NV | J12: 0.0194 | K12: 1547.22 | L12: 614.06
A13: S&P Total return | B13: INDEXSP:SP500TR | C13: 15225.18 | D13: 0.62 | G13: Date | H13: Close
F14: ASTS | G14: 46120 | H14: 96.46 | I14: AST SpaceMobile Inc | J14: -0.0503 | K14: 129.87 | L14: 20.26
G15: Date | H15: Close
F16: AVGO | G16: 46120 | H16: 350.63 | I16: Broadcom Inc | J16: 0.0122 | K16: 414.61 | L16: 161.62
G17: Date | H17: Close
F18: BRK.B | G18: 46120 | H18: 479.75 | I18: Berkshire Hathaway Inc Class B | J18: 0.0114 | K18: 542.07 | L18: 455.19
G19: Date | H19: Close
F20: CAT | G20: 46120 | H20: 771.58 | I20: Caterpillar Inc | J20: 0.0201 | K20: 795.52 | L20: 279.8
G21: Date | H21: Close
F22: DRVN | G22: 46120 | H22: 12.53 | I22: Driven Brands Holdings Inc | J22: 0.0104 | K22: 19.74 | L22: 9.8
G23: Date | H23: Close
F24: ENSG | G24: 46120 | H24: 204.79 | I24: Ensign Group Inc | J24: -0.0158 | K24: 218 | L24: 118.73
G25: Date | H25: Close
F26: FIX | G26: 46120 | H26: 1525.16 | I26: Comfort Systems USA Inc | J26: 0.0323 | K26: 1601.9 | L26: 321.95
G27: Date | H27: Close
F28: GE | G28: 46120 | H28: 308.06 | I28: General Electric Co | J28: 0.0161 | K28: 348.48 | L28: 175.05
G29: Date | H29: Close
F30: GEV | G30: 46120 | H30: 936.07 | I30: GE Vernova Inc | J30: 0.0341 | K30: 979.43 | L30: 303.1
G31: Date | H31: Close
F32: GLW | G32: 46120 | H32: 165.1 | I32: Corning Inc | J32: 0.0285 | K32: 172.22 | L32: 40.16
G33: Date | H33: Close
F34: GOOG | G34: 46120 | H34: 314.74 | I34: Alphabet Inc Class C | J34: 0.0052 | K34: 350.15 | L34: 148.4
G35: Date | H35: Close
F36: GOOGL | G36: 46120 | H36: 317.32 | I36: Alphabet Inc Class A | J36: 0.0036 | K36: 349 | L36: 146.1
G37: Date | H37: Close
F38: GPGI | G38: 46120 | H38: 16.88 | I38: GPGI Inc | J38: -0.029 | K38: 25.93 | L38: 15.48
G39: Date | H39: Close
F40: GPOR | G40: 46120 | H40: 202.29 | I40: Gulfport Energy Corp | J40: 0.0051 | K40: 225.78 | L40: 156.94
G41: Date | H41: Close
F42: HCA | G42: 46120 | H42: 505.12 | I42: HCA Healthcare Inc | J42: 0.0041 | K42: 556.52 | L42: 314.43
G43: Date | H43: Close
F44: HON | G44: 46120 | H44: 232.47 | I44: Honeywell International Inc | J44: 0.0154 | K44: 248.18 | L44: 168.99
G45: Date | H45: Close
F46: IVV | G46: 46120 | H46: 678.99 | I46: iShares Core S&P 500 ETF | J46: 0.0059 | K46: 700.96 | L46: 510.91
G47: Date | H47: Close
F48: JPM | G48: 46120 | H48: 307.97 | I48: JPMorgan Chase & Co | J48: 0.0077 | K48: 337.25 | L48: 220.1
G49: Date | H49: Close
F50: KGS | G50: 46120 | H50: 60.23 | I50: Kodiak Gas Services Inc | J50: 0.0025 | K50: 61.48 | L50: 30.06
G51: Date | H51: Close
F52: LIN | G52: 46120 | H52: 500.48 | I52: Linde PLC | J52: 0.0056 | K52: 510.65 | L52: 387.78
G53: Date | H53: Close
F54: LLY | G54: 46120 | H54: 953.3 | I54: Eli Lilly And Co | J54: 0.002 | K54: 1133.95 | L54: 623.78
G55: Date | H55: Close
F56: LULU | G56: 46120 | H56: 158.86 | I56: Lululemon Athletica Inc | J56: 0.0482 | K56: 340.25 | L56: 143.96
G57: Date | H57: Close
F58: MA | G58: 46120 | H58: 507.12 | I58: Mastercard Inc | J58: -0.0053 | K58: 601.77 | L58: 480.5
G59: Date | H59: Close
F60: MCW | G60: 46120 | H60: 6.99 | I60: Mister Car Wash Inc | J60: 0 | K60: 7.98 | L60: 4.61
G61: Date | H61: Close
F62: META | G62: 46120 | H62: 612.42 | I62: Meta Platforms Inc | J62: 0.0261 | K62: 796.25 | L62: 479.8
G63: Date | H63: Close
F64: MSFT | G64: 46120 | H64: 374.33 | I64: Microsoft Corp | J64: -0.0034 | K64: 555.45 | L64: 355.67
G65: Date | H65: Close
F66: NEE | G66: 46120 | H66: 94.17 | I66: NextEra Energy Inc | J66: 0.0033 | K66: 96.21 | L66: 63.64
G67: Date | H67: Close
F68: NFG | G68: 46120 | H68: 95.58 | I68: National Fuel Gas Co | J68: -0.0058 | K68: 97.06 | L68: 72.47
G69: Date | H69: Close
F70: NFLX | G70: 46120 | H70: 99.39 | I70: Netflix Inc | J70: 0.0272 | K70: 134.12 | L70: 75.01
G71: Date | H71: Close
F72: NVDA | G72: 46120 | H72: 182.08 | I72: NVIDIA Corp | J72: 0.0102 | K72: 212.19 | L72: 95.04
G73: Date | H73: Close
F74: OEF | G74: 46120 | H74: 330.15 | I74: iShares S&P 100 ETF | J74: 0.0081 | K74: 349.08 | L74: 245.57
G75: Date | H75: Close
F76: PEP | G76: 46120 | H76: 154.8 | I76: PepsiCo Inc | J76: 0.0174 | K76: 171.48 | L76: 127.6
G77: Date | H77: Close
F78: PG | G78: 46120 | H78: 144.9 | I78: Procter & Gamble Co | J78: 0.0121 | K78: 171.65 | L78: 137.62
G79: Date | H79: Close
F80: PLTR | G80: 46120 | H80: 140.76 | I80: Palantir Technologies Inc | J80: -0.0726 | K80: 207.52 | L80: 84.14
G81: Date | H81: Close
F82: PM | G82: 46120 | H82: 160.94 | I82: Philip Morris International Inc. | J82: 0.0019 | K82: 191.3 | L82: 142.11
G83: Date | H83: Close
F84: SOLS | G84: 46120 | H84: 83.35 | I84: Solstice Advanced Materials Inc | J84: -0.0065 | K84: 84.44 | L84: 40.43
G85: Date | H85: Close
F86: TSLA | G86: 46120 | H86: 343.25 | I86: Tesla Inc | J86: 0.0068 | K86: 498.83 | L86: 222.79
G87: Date | H87: Close
F88: V | G88: 46120 | H88: 308.96 | I88: Visa Inc | J88: -0.0022 | K88: 375.51 | L88: 293.89
G89: Date | H89: Close
F90: VMC | G90: 46120 | H90: 292.58 | I90: Vulcan Materials Co | J90: 0.0015 | K90: 331.09 | L90: 229.3
G91: Date | H91: Close
F92: VRT | G92: 46120 | H92: 281.03 | I92: Vertiv Holdings Co | J92: 0.0235 | K92: 291 | L92: 65.68
G93: Date | H93: Close
F94: WMT | G94: 46120 | H94: 127.26 | I94: Walmart Inc | J94: 0.0147 | K94: 134.69 | L94: 88.16
G95: Date | H95: Close
F96: XLB | G96: 46120 | H96: 51.75 | I96: State Street Materials Select Sector SPDR ETF | J96: -0.0015 | K96: 54.14 | L96: 36.88
G97: Date | H97: Close
F98: XLC | G98: 46120 | H98: 113.81 | I98: State Street Com Svc Sel Sec SPDR ETF | J98: 0.004 | K98: 120.39 | L98: 87.49
G99: Date | H99: Close
F100: XLE | G100: 46120 | H100: 58.05 | I100: State Street Energy Select Sector SPDR ETF | J100: -0.0124 | K100: 63.46 | L100: 37.24
...

Sheet LH_Holding_Custody T
A1: Account - GSP | B1: Price Date | C1: Report Run Date (CDT) | D1: ISIN | E1: Local Price | F1: Security Description 1 | G1: TICKER | H1: As Of Date | I1: Market Value Local-Posted Basis | J1: Units - Posted Basis | K1: Units - Settled Basis | L1: Market Value Traded Base
A2: 658585 | B2: 46026 | C2: 46026.963 | D2: US30303M1027 | E2: 579.23 | F2: META PLATFORMS INC USD 0.000006 | G2: META US | H2: 46113 | I2: 132643.67 | J2: 229 | K2: 229 | L2: 132643.67 | N2: META | O2: US | P2: =+J2-K2 -> 0
A3: 658585 | B3: 46026 | C3: 46026.963 | D3: US7134481081 | E3: 154.65 | F3: PEPSICO INC USD 0.017 | G3: PEP US | H3: 46113 | I3: 68355.3 | J3: 442 | K3: 635 | L3: 98202.75 | N3: PEP | O3: US | P3: =+J3-K3 -> -193
A4: 658585 | B4: 46026 | C4: 46026.963 | D4: US7427181091 | E4: 144.09 | F4: PROCTER + GAMBLE CO NPV | G4: PG US | H4: 46113 | I4: 53601.48 | J4: 372 | K4: 372 | L4: 53601.48 | N4: PG | O4: US | P4: =+J4-K4 -> 0
A5: 658585 | B5: 46026 | C5: 46026.963 | D5: US60770K1079 | E5: 50.03 | F5: MODERNA INC USD 0.0001 | G5: MRNA US | H5: 46113 | I5: 39523.7 | J5: 790 | K5: 790 | L5: 39523.7 | N5: MRNA | O5: US | P5: =+J5-K5 -> 0
A6: 658585 | B6: 46026 | C6: 46026.963 | D6: US81369Y8865 | E6: 46.11 | F6: STATE STREET UTILITIES SELECT SECTO | G6: XLU US | H6: 46113 | I6: 110387.34 | J6: 2394 | K6: 2394 | L6: 110387.34 | N6: XLU | O6: US | P6: =+J6-K6 -> 0
A7: 658585 | B7: 46026 | C7: 46026.963 | D7: US30231G1022 | E7: 160.78 | F7: EXXON MOBIL CORP NPV | G7: XOM US | H7: 46113 | I7: 132321.94 | J7: 823 | K7: 823 | L7: 132321.94 | N7: XOM | O7: US | P7: =+J7-K7 -> 0
A8: 658585 | B8: 46026 | C8: 46026.963 | D8: US69608A1088 | E8: 146.49 | F8: PALANTIR TECHNOLOGIES INC USD 0.001 | G8: PLTR US | H8: 46113 | I8: 52296.93 | J8: 357 | K8: 357 | L8: 52296.93 | N8: PLTR | O8: US | P8: =+J8-K8 -> 0
A9: 658585 | B9: 46026 | C9: 46026.963 | D9: US50012A1088 | E9: 57.9 | F9: KODIAK GAS SVCS INC USD 0.01 | G9: KGS US | H9: 46113 | I9: 161888.4 | J9: 2796 | K9: 2796 | L9: 161888.4 | N9: KGS | O9: US | P9: =+J9-K9 -> 0
A10: 658585 | B10: 46026 | C10: 46026.963 | D10: US81369Y8030 | E10: 134.91 | F10: STATE STREET TECHNOLOGY SELECT SECT | G10: XLK US | H10: 46113 | I10: 613031.04 | J10: 4544 | K10: 4544 | L10: 613031.04 | N10: XLK | O10: US | P10: =+J10-K10 -> 0
A11: 658585 | B11: 46026 | C11: 46026.963 | D11: US81369Y8030 | E11: 134.91 | F11: STATE STREET TECHNOLOGY SELECT SECT | G11: XLK US | H11: 46113 | I11: 68129.55 | J11: 505 | K11: 505 | L11: 68129.55 | N11: XLK | O11: US | P11: =+J11-K11 -> 0
A12: 658585 | B12: 46026 | C12: 46026.963 | D12: US81369Y3080 | E12: 81.46 | F12: STATE STREET CONSUMER STAPLES SELEC | G12: XLP US | H12: 46113 | I12: 90094.76 | J12: 1106 | K12: 1106 | L12: 90094.76 | N12: XLP | O12: US | P12: =+J12-K12 -> 0
A13: 658585 | B13: 46026 | C13: 46026.963 | D13: US7820111000 | E13: 21.94 | F13: RUSH STR INTERACTIVE INC USD 0.0001 | G13: RSI US | H13: 46113 | I13: 21194.04 | J13: 966 | K13: 0 | L13: 0 | N13: RSI | O13: US | P13: =+J13-K13 -> 966
... A78: 658585 | B78: 46026 | C78: 46026.963 | D78: US64110L1061 | E78: 95.55 | F78: NETFLIX INC USD 0.001 | G78: NFLX US | H78: 46113 | I78: 42997.5 | J78: 450 | K78: 450 | L78: 42997.5 | N78: NFLX | O78: US | P78: =+J78-K78 -> 0
A79: 658585 | B79: 46026 | C79: 46026.963 | D79: X9X9USDUTMP2 | E79: 1 | F79: UTM MCC POOL ACTIVE RESERVE | H79: 46113 | I79: 127655.16 | J79: 127655.16 | K79: 127655.16 | L79: 127655.16
